{
"title": "Asmaul Husna - 99 Names of Allah (সম্পূর্ণ বিস্তারিত)",
"language": "bn",
"count": 99,
"names": [
{
"id": 1,
"name_ar": "ٱللّٰهُ",
"name_bn": "আল্লাহ",
"meaning_bn": "একমাত্র সৃষ্টিকর্তা, সর্বশক্তিমান, একেবারেই অনন্য ইলাহ",
"virtues": "‘আল্লাহ’ হচ্ছে সব নামের মূল ও সর্বোচ্চ নাম; এতে সমস্ত রুপ, গুণ ও অধিকার সংকলিত। এ নামের স্মরণ হৃদয়কে কেন্দ্রীভূত করে এবং ইমান দৃঢ়তা বাড়ায়।",
"practices": "১) দিনের প্রতিটি কাজে আল্লাহর নাম নিয়ে শুরু করা (বিসমিল্লাহ)।\n২) কষ্টে বা সুখে নিয়মিত 'লা ইলাহা ইল্লাল্লাহ' উচ্চারণ করা।\n৩) সন্তানের প্রথম শিক্ষা হিসেবে এই নাম শেখানো ও স্মরণ করানো।"
},
{
"id": 2,
"name_ar": "الرَّحْمَٰنُ",
"name_bn": "আর-রাহমান",
"meaning_bn": "পরম করুণাময় — সকলের প্রতি ব্যাপক ও সার্বজনীন করুণা",
"virtues": "আর-রাহমান আল্লাহর সার্বজনীন করুণা ও দয়াকে প্রকাশ করে; প্রতিটি সৃষ্টি—মানুষ, প্রাণী, এমনকি উদ্ভিদও তাঁর করুণার অংশ। এই নাম স্মরণে হৃদয় নরম হয়ে সহানুভূতি বৃদ্ধি পায়।",
"practices": "১) সূরা ফাতিহা ও অন্যান্য দোআসমূহের সময় 'র-রাহমান' উচ্চারণ করা।\n২) অন্যের প্রতি করুণা দেখিয়ে আল্লাহর করুণার অনুকরণ করা।\n৩) কষ্টে পড়লে 'র-রাহমান' স্মরণ করে দোয়া ও ভরসা রাখা।"
},
{
"id": 3,
"name_ar": "الرَّحِيمُ",
"name_bn": "আর-রাহীম",
"meaning_bn": "পরম দয়ালু — বিশেষত বিশ্বাসীদের প্রতি দয়া",
"virtues": "আর-রাহীম আল্লাহর বিশেষ দয়াশীলতাকে নির্দেশ করে; বিশ্বাসীদের প্রতি তাঁর অনুগ্রহ ও রহমত নিবিড়। এটি ভরসা ও শান্তি দান করে।",
"practices": "১) প্রতিদিনের নামাজে ও দোয়ায় রাহীম স্মরণ করা।\n২) অপরকে ক্ষমা করে আল্লাহর রাহীম হওয়ার অনুকরণ করা।\n৩) রাতে তিসরা/তাসবিহের সময় এই নাম বলে মনকে প্রশান্ত করা।"
},
{
"id": 4,
"name_ar": "ٱلْمَلِكُ",
"name_bn": "আল-মালিক",
"meaning_bn": "সর্বাধিপতি, সমস্ত রাজ্যের একমাত্র মালিক",
"virtues": "আল-মালিক নামটি আল্লাহর সার্বভৌমত্ব ও শাসনাধিকারকে ব্যক্ত করে; সব নিয়ন্ত্রণ ও ক্ষমতা তাঁর হাতে। স্মরণে অনতিব বড় দায় থেকে মুক্ত হওয়ার অনুরোধ সৃষ্টি হয়।",
"practices": "১) বড় সিদ্ধান্ত নেওয়ার আগে আল্লাহর সুমিটে ভরসা রাখা (তাওয়াক্কুল)।\n২) রাজ্য, সত্তা ও নিয়ন্ত্রণ সম্পর্কে আল্লাহর কাছে সমর্পণ করা।\n৩) কর্তৃত্ব ও ক্ষমতার সাথে নম্রতা বজায় রাখা।"
},
{
"id": 5,
"name_ar": "ٱلْقُدُّوسُ",
"name_bn": "আল-কুদ্দুস",
"meaning_bn": "পরম পবিত্র, ত্রুটিমুক্ত",
"virtues": "আল-কুদ্দুস নামটি আল্লাহর সম্পূর্ণ পবিত্রতা ও দোষমুক্তি নির্দেশ করে; প্রতিটি কুসংস্কার ও ত্রুটি তাঁর থেকে দূরে।",
"practices": "১) আত্মশুদ্ধির চেষ্টা ও তওবা করা।\n২) পবিত্র কাজ ও ইবাদত বৃদ্ধির মাধ্যমে আল্লাহর ক্ষুদ্রতায় বিনয় প্রকাশ করা।\n৩) জীবনের ক্রিয়াকলাপে পবিত্রতা বজায় রাখার নিয়ম গ্রহণ করা।"
},
{
"id": 6,
"name_ar": "ٱلسَّلَامُ",
"name_bn": "আস-সালাম",
"meaning_bn": "শান্তির ও নিরাপত্তার দাতা",
"virtues": "আস-সালাম আল্লাহর শান্তি প্রদানের ক্ষমতা প্রকাশ করে; যারা তাঁর কাছে শরণেন তারা নিরাপদ ও শান্তিতে থাকে।",
"practices": "১) অন্যকে সালাম দিয়ে শুভেচ্ছা জানানো।\n২) দোয়ায় শান্তি ও নিরাপত্তা কামনা করা।\n৩) আত্মার শান্তি পেতে নিয়মিত ধ্যানধারণায় এই নাম স্মরণ করা।"
},
{
"id": 7,
"name_ar": "ٱلْمُؤْمِنُ",
"name_bn": "আল-মুমিন",
"meaning_bn": "নিরাপত্তা প্রদানকারী, বিশ্বাস প্রতিষ্ঠাকারী",
"virtues": "আল-মুমিন নামটি আল্লাহর থেকে সুরক্ষা ও নিশ্চিত নিরাপত্তা পাওয়ার প্রতিশ্রুতি বহন করে।",
"practices": "১) ভয়ের মুহূর্তে আল্লাহর কাছে নিরাপত্তা প্রার্থনা করা।\n২) অপরকে নিরাপত্তা ও সেবায় সহায়তা করা।\n৩) বিশ্বাস দৃঢ় করতে নিয়মিত নাম–আয়াত পাঠ করা।"
},
{
"id": 8,
"name_ar": "ٱلْمُهَيْمِنُ",
"name_bn": "আল-মুহাইমিন",
"meaning_bn": "তত্ত্বাবধায়ক, রক্ষাকর্তা",
"virtues": "আল-মুহাইমিন সবকিছুকে তত্ত্বাবধান করেন; তিনি সৃষ্টির প্রতিবেশ ও গোপন বিষয়ও জানেন এবং রক্ষা করেন।",
"practices": "১) প্রতিদিন সকালে আল্লাহর তত্ত্বাবধানে কৃতজ্ঞতা ব্যক্ত করা।\n২) জীবনের প্রতিটি দিক আল্লাহর তত্ত্বাবধানে ছেড়ে দেওয়ার অভ্যাস করা।\n৩) বাধা-প্রতিবন্ধকতায় আল্লাহর হুকুম মান্য করে ধৈর্য ধারণ করা।"
},
{
"id": 9,
"name_ar": "ٱلْعَزِيزُ",
"name_bn": "আল-আজীজ",
"meaning_bn": "দুর্জয়, গর্বিত ও সম্মানিত শক্তি",
"virtues": "আল-আজীজ সব শক্তির অধিপতি; তিনি অনীহা, অপমান বা প্রতিহিংসাকে প্রতিহত করতে পারবেন। তাঁর কাছে সাহায্য প্রার্থনা করলে মর্যাদা ও শক্তি লাভ করা যায়।",
"practices": "১) দুর্ভেদ্য বিপদে আল্লাহর কাছে আশ্রয় চাও।\n২) অহংকার নয়, বরং আল্লাহর শক্তিকে স্মরণ করে নম্র হও।\n৩) অন্যায়ের বিরুদ্ধে দাঁড়াতে আল্লাহর সাহায্য কামনা করা।"
},
{
"id": 10,
"name_ar": "ٱلْجَبَّارُ",
"name_bn": "আল-জব্বার",
"meaning_bn": "বাধ্যতামূলক শক্তিধর, ভাঙ্গা-কচলাকে মেরামতকারী",
"virtues": "আল-জব্বার ভাঙা-চুরোকে মেরামত করার ক্ষমা রাখেন; তিনি অত্যন্ত শক্তিশালী ও আচম্বিতে ব্যবস্থা গ্রহণকারী।",
"practices": "১) হৃদয়ের ভাঙন ও হতাশা কাটাতে আল্লাহর কাছে দোয়া করা।\n২) সমাজে অনাচার-অবিচারের বিরুদ্ধে ন্যায় প্রতিষ্ঠা করা।\n৩) ব্যক্তিগত দুর্বলতা সইতে আল্লাহর সাহায্য চাও।"
},
{
"id": 11,
"name_ar": "ٱلْمُتَكَبِّرُ",
"name_bn": "আল-মুতাকাব্বির",
"meaning_bn": "পরম মহিমান্বিত — সর্বোচ্চ গৌরবশালী (মানুষ যাতে অহংকার না করে)",
"virtues": "আল-মুতাকাব্বিরের মহিমা অপরিসীম; তিনি সকল গৌরব ও প্রশংসার একমাত্র অধিকারী। মানুষের উচিত অহংকার ও ফুঁসে ওঠা পরিহার করে তাঁর সম্মান পালন করা।",
"practices": "১) অহংকার পরিহার করে নম্রতা অনুশীলন করা।\n২) আল্লাহর মহিমা বিজ্ঞাপন করে কৃতজ্ঞতা প্রকাশ করা।\n৩) নিজের কৃতিত্ব আল্লাহর অনুগ্রহ বলে মানা।"
},
{
"id": 12,
"name_ar": "ٱلْخَالِقُ",
"name_bn": "আল-খালিক",
"meaning_bn": "স্রষ্টা, নব সৃষ্টি ও রূপকার",
"virtues": "আল-খালিক সবকিছুর স্রষ্টা; তিনি জিনিসকে নির্দিষ্ট রূপে সৃষ্টি ও রূপান্তর করতে সক্ষম। তাঁর শিল্প-সৃজনের মধ্যে নিখুঁত মিশ্রণ ও উদ্দেশ্য বিদ্যমান।",
"practices": "১) সৃষ্টির সৌন্দর্য দেখে কৃতজ্ঞতা জানানো।\n২) সৃষ্টির রক্ষায় আত্মীয়তায় কাজ করা (পরিবেশ রক্ষা)।\n৩) নতুন কাজ শুরুতে আল্লাহর নির্দেশ ও সহায়তা চাওয়া।"
},
{
"id": 13,
"name_ar": "ٱلْبَارِئُ",
"name_bn": "আল-বারি'",
"meaning_bn": "উদ্ভাবক, যিনি সৃষ্টিকে সুনিয়ন্ত্রিতভাবে গঠন করেন",
"virtues": "আল-বারি' সৃষ্টির রচয়িতা; তিনি প্রতিটি জীব ও বস্তুকে উপযুক্তভাবে বিন্যস্ত করেন। তাঁর পরিকল্পনা এবং সৃজনশীলতা অপরিসীম।",
"practices": "১) সৃষ্টি নিয়ে চিন্তা-মনন করে আল্লাহর প্রতি কৃতজ্ঞতা দেখানো।\n২) নিজের কাজগুলো সুন্দরভাবে সজ্জিত করার চেষ্টা করা।\n৩) সৃজনশীল কাজের সময় আল্লাহর সাথে অভিভূত হওয়া।"
},
{
"id": 14,
"name_ar": "ٱلْمُصَوِّرُ",
"name_bn": "আল-মুসাওয়ার (আল-মুসব্বির)",
"meaning_bn": "রূপ-প্রদানকারী, প্রতিটি বস্তুকে নিদর্শন করে গড়ে তোলেন",
"virtues": "আল-মুসাওয়ার প্রতিটি সত্তাকে তার স্বতন্ত্র রূপ দেন; এই নাম সৃষ্টি বৈচিত্র্য ও সৌন্দর্যের উত্স।",
"practices": "১) সৃষ্টির ভিন্নতা দেখে ধন্যবাদ জ্ঞাপন করা।\n২) শিল্প ও সৃজনশীলতায় শরীয়ত সম্মত সীমা বজায় রাখা।\n৩) নিজ রূপ-গঠনে আল্লাহর করুণার স্মরণ রাখা।"
},
{
"id": 15,
"name_ar": "ٱلْغَفَّارُ",
"name_bn": "আল-গফফার",
"meaning_bn": "অপূর্বভাবে ক্ষমাশীল, বারবার ক্ষমা করে দেওয়া",
"virtues": "আল-গফফার বারবার ও বহুমাত্রিকভাবে ক্ষমা দানকারী; প্রতিটি সৎ তাওবার জন্য দ্বার খোলা।",
"practices": "১) পাপ হলে আন্তরিকভাবে তওবা করা এবং আল্লাহর কাছে ক্ষমা চাওয়া।\n২) অন্যদেরও ক্ষমা করে দিয়ে আল্লাহর ক্ষমা প্রার্থনা করা।\n৩) রাতে দোয়া-তারাবিতে আল্লাহর এই নাম দিয়ে রোগভিত্তিক তওবা করা।"
},
{
"id": 16,
"name_ar": "ٱلْقَهَّارُ",
"name_bn": "আল-ক্বাহহার",
"meaning_bn": "পরাক্রমশালী, যে সর্বশক্তি দিয়ে জয়লাভ করেন",
"virtues": "আল-ক্বাহহার সমস্ত বাধা ও শক্তিকে জয় করেন; বিপদের সময় তাঁরই কাছে ভরসা।",
"practices": "১) বিপদের মুহূর্তে আল্লাহর সহায়তা চাওয়া।\n২) ক্ষমতা পাওয়ার পরে নম্রতা বজায় রাখা।\n৩) সামাজিক ও নৈতিক অনাচার দূর করার জন্য আল্লাহর সাহায্য প্রার্থনা করা।"
},
{
"id": 17,
"name_ar": "ٱلْوَهَّابُ",
"name_bn": "আল-ওাহ্হাব",
"meaning_bn": "অনুদানকারী, অশেষ দানকারী",
"virtues": "আল-ওাহ্হাব বিনামূল্যে অনেক অনুদান দান করেন—মালিকানাধীন বরকত ও রহমত প্রদান করেন।",
"practices": "১) রিজিক, ইলম, হিকমত চেয়ে আল্লাহর কাছে দোয়া করা।\n২) প্রাপ্ত বরকত ভাগ করে দরিদ্রদের সাহায্য করা।\n৩) দান-খায়েলা বাড়িয়ে আল্লাহর ওহাবিত্বকে স্মরণ করা।"
},
{
"id": 18,
"name_ar": "ٱلْرَّزَّاقُ",
"name_bn": "আর-রজ্জাক",
"meaning_bn": "রিযিক দানকারী, প্রদায়ক",
"virtues": "আর-রজ্জাক রিজিকের চাবিকাঠি; তিনি যা ইচ্ছা, যেখানে ইচ্ছা, যাকে ইচ্ছা, রিজিক দান করেন।",
"practices": "১) রোজগারের জন্য ইমান ও পরিশ্রমের সাথে আল্লাহর কাছে দোয়া করা।\n২) প্রাপ্ত রিজিক থেকে নিয়মিত সদকা করা।\n৩) রিজিকহীনতার সময় ধৈর্য ও বিশ্বাস বজায় রাখা।"
},
{
"id": 19,
"name_ar": "ٱلْفَتَّاحُ",
"name_bn": "আল-ফাত্তাহ",
"meaning_bn": "দরজা খোলেন, সাফল্য ও সমাধান প্রদানকারী",
"virtues": "আল-ফাত্তাহ সমস্যার সমাধানকারী; তিনি পথ ও সুযোগ খুলে দেন। তাঁর সাহায্যে কঠিন বিষয়ও সমাধান সম্ভব।",
"practices": "১) কঠিন কাজ শুরু করার আগে আল্লাহর দরজা খোলার জন্য দোয়া করা।\n২) পরীক্ষায় ও ব্যবসায় সাফল্যের জন্য এই নাম স্মরণ করা।\n৩) তাকওয়া ও ধৈর্যের মাধ্যমে আল্লাহর দান প্রাপ্তির জন্য সচেষ্ট থাকা।"
},
{
"id": 20,
"name_ar": "ٱلْعَلِیُّ",
"name_bn": "আল-আলী",
"meaning_bn": "সর্বোচ্চ, উচ্চতম মর্যাদাসম্পন্ন",
"virtues": "আল-আলী আল্লাহর উচ্চতা ও মহত্ত্ব প্রকাশ করে; তিনি সর্বোচ্চ মর্যাদা ও গৌরবের অধিকারী।",
"practices": "১) নিজের লক্ষ্যগুলো আল্লাহর প্রতি সম্মান রেখে স্থাপন করা।\n২) অহংকার ছাড়া উচচ উদ্দেশ্য নিয়ে কাজ করা।\n৩) আল্লাহর উচ্চতার স্মরণে বিনয়ী হওয়া।"
},
{
"id": 21,
"name_ar": "ٱلْكَبِيرُ",
"name_bn": "আল-ক্ববীর",
"meaning_bn": "বৃহৎ ও অতি মহৎ",
"virtues": "আল-ক্ববীরের মহত্ত্ব সীমাহীন; তিনি প্রতিটি কিছুকে মহানভাবে ধারণ করেন।",
"practices": "১) সৃষ্টির বড়ত্ব দেখে আল্লাহর কাছে কৃতজ্ঞতা প্রকাশ করা।\n২) জীবনের ক্ষুদ্র ঘটনাগুলিকে বড় করে না দেখা, ধৈর্য রাখা।"
},
{
"id": 22,
"name_ar": "ٱلْحَفِيظُ",
"name_bn": "আল-হাফিজ",
"meaning_bn": "রক্ষাকারী, সংরক্ষণকারী",
"virtues": "আল-হাফিজ সমস্ত সৃষ্টিকে রক্ষা ও ধারণ করেন; তিনি ক্ষতি থেকে রক্ষা করেন।",
"practices": "১) রাতভর আল্লাহর রক্ষার জন্য দোয়া করা।\n২) মূল্যবান জিনিস ও সম্পর্ক রক্ষায় সতর্ক থাকা।\n৩) ভ্রমণ বা বিপদে উঠার সময় এই নাম স্মরণ করা।"
},
{
"id": 23,
"name_ar": "ٱلْمُقيِتُ",
"name_bn": "আল-মুকীত",
"meaning_bn": "জীবিকা প্রদানকারী, রেখাপথের রক্ষক",
"virtues": "আল-মুকীত মানুষের জীবন চালানোর জন্য প্রয়োজনীয় সহায়তা প্রদান করেন; তিনি রুজির এবং মৌলিক ধারাকে নিয়ন্ত্রন করেন।",
"practices": "১) প্রতিদিন সকালে রুজির জন্য আল্লাহর কাছে কৃতজ্ঞতা জানানো।\n২) উপার্জনে পরিশ্রমের সঙ্গে আল্লাহর কাছে দোয়া করা।"
},
{
"id": 24,
"name_ar": "ٱلْحَسِيبُ",
"name_bn": "আল-হাসিব",
"meaning_bn": "হিসাব রাখেন, প্রত্যেক কাজের হিসাব বিদ্যা রাখেন",
"virtues": "আল-হাসিব প্রতিটি কাজের হিসাব রাখেন—ভাল ও মন্দ সবকিছু তাঁর নজরে।",
"practices": "১) নিজের আমলের হিসাব রেখে আত্মসমালোচনা করা।\n২) পরিশোধিত জীবনযাত্রার মাধ্যমে আল্লাহর সন্তুষ্টি অর্জনের চেষ্টা করা।"
},
{
"id": 25,
"name_ar": "ٱلْجَلِيلُ",
"name_bn": "আল-জালীল",
"meaning_bn": "মহিমান্বিত ও গর্বিত",
"virtues": "আল-জালীল তাঁর মহিমা ও মর্যাদা দ্বারা আচ্ছন্ন; তিনি শ্রদ্ধার যোগ্য।",
"practices": "১) আল্লাহর গুণাবলি স্মরণ করে কৃতজ্ঞতা জানানো।\n২) তাঁর মহিমা অনুযায়ী নিজেকে নম্র করা।"
},
{
"id": 26,
"name_ar": "ٱلْكَرِيمُ",
"name_bn": "আল-করীম",
"meaning_bn": "দয়াশীল ও উদার — অশেষ দানকারী",
"virtues": "আল-করীম উদারতার প্রতীক; তিনি অপ্রত্যাশিতভাবে উপকার দান করেন।",
"practices": "১) দান-দান ও সহায়তা বাড়িয়ে আল্লাহর উদারতা অনুসরণ করা।\n২) প্রাপ্ত কল্যাণ থেকে কৃতজ্ঞতা প্রকাশ করা।"
},
{
"id": 27,
"name_ar": "ٱلْرَّقِيبُ",
"name_bn": "আর-রকীব",
"meaning_bn": "নজরদার, প্রত্যক্ষ পর্যবেক্ষক",
"virtues": "আর-রকীব সবকিছু নিরীক্ষণ করেন; গোপনীয়তাও তাঁর দৃষ্টির বাইরে নেই।",
"practices": "১) গোপন এবং প্রকাশ্য আচরণে সতর্ক থাকা।\n২) অন্যের প্রতি ন্যায্যতা ও সৎ আচরণ বজায় রাখা।"
},
{
"id": 28,
"name_ar": "ٱلْمُجِيبُ",
"name_bn": "আল-মুজীব",
"meaning_bn": "দোয়া কবুলকারী, আহ্বানকর্তার প্রতিক্রিয়া-দাতা",
"virtues": "আল-মুজীব মনোবাসনা ও দোয়াগুলোর প্রতি সাড়া দেন; তিনি অনুরোধ শোনেন ও প্রতিক্রিয়া দেন।",
"practices": "১) দোয়া করার সময় যথার্থতা ও ধৈর্য রাখুন—আল-মুজীব শুনেন।\n২) বিশেষ প্রয়োজন অনুভব করলে সৎ ও বিনীতভাবে দোয়া করা।\n৩) দোয়া কবুল হলে কৃতজ্ঞতা প্রদর্শন করা ও অন্যের জন্য দোয়া করা।"
},
{
"id": 29,
"name_ar": "ٱلْوَاسِعُ",
"name_bn": "আল-ওয়াসি'",
"meaning_bn": "প্রশস্ত, বিস্তৃত (মর্জি ও রহমত অসীম)",
"virtues": "আল-ওয়াসি' আল্লাহর ক্ষমা ও রহমতের বিশালতা প্রকাশ করে; তাঁর দান সীমাহীন।",
"practices": "১) আল্লাহর প্রশস্ততার ওপর ভরসা রেখে দুঃখ-সঙ্কট মোকাবেলা করা।\n২) বড় হৃদয়ে অন্যকে গ্রহণ করা ও সহযোগিতা করা।"
},
{
"id": 30,
"name_ar": "ٱلْحَكِيمُ",
"name_bn": "আল-হাকীম",
"meaning_bn": "পরম বিচক্ষণ ও জ্ঞানী",
"virtues": "আল-হাকীম সমগ্র পরিকল্পনায় পূর্ণ জ্ঞান ও ন্যায়বিচার প্রয়োগ করেন; তাঁর হুকুম সবসময় সাধ্যবান ও উপযুক্ত।",
"practices": "১) সিদ্ধান্ত নেওয়ার আগে জ্ঞান অর্জনে প্রচেষ্টা করা।\n২) সত্য ও ন্যায়-ভিত্তিক পন্থা অনুসরণ করা।\n৩) জীবনের পরিস্থিতিতে আল্লাহর حکمت অনুসন্ধান করা।"
},
{
"id": 31,
"name_ar": "ٱلْوَدُودُ",
"name_bn": "আল-ওদুদ",
"meaning_bn": "অত্যন্ত প্রেমময়, পরম ভালোবাসার সূত্র",
"virtues": "আল-ওদুদ আল্লাহর মানুষের প্রতি অফুরন্ত ভালোবাসা নির্দেশ করে; বিশেষত সৎ ও নম্র হৃদয়ের প্রতি।",
"practices": "১) আল্লাহর ভালোবাসা উপার্জনের জন্য ইমান ও নৈতিকতা টেকসই করা।\n২) অন্যকে ভালোবাসা ও সহানুভূতি দেখানো।\n৩) ভক্তিমুলক আমল ও ধৈর্য বৃদ্ধি করা।"
},
{
"id": 32,
"name_ar": "ٱلْمَجِيدُ",
"name_bn": "আল-মাজীদ",
"meaning_bn": "মহিমান্বিত, গৌরবময়",
"virtues": "আল-মাজীদ আল্লাহর মহিমা ও গৌরবকে বিকাশ করে; তিনি সম্মান ও মর্যাদার পূর্ণ উৎস।",
"practices": "১) কোরআন-তেলাওয়াত ও নামাজে আল্লাহর মাহাত্ম্য উচ্চারণ করা।\n২) আল্লাহর প্রতি শ্রদ্ধাশীল আচরণ বজায় রাখা।"
},
{
"id": 33,
"name_ar": "ٱلْبَاعِثُ",
"name_bn": "আল-বাঈছ",
"meaning_bn": "পুনরুত্থানকারী, জীবন-প্রদান ও প্রেরণকারী",
"virtues": "আল-বাঈছ কিয়ামত ও পুনরুত্থানের ক্ষমতা ধারণ করেন; তিনি মৃত্যুর পরে জীবন প্রদান করবেন।",
"practices": "১) আখেরাতের স্মরণে নেক আমল বৃদ্ধি করা।\n২) মৃত্যুর পর জীবনের জন্য প্রস্তুতি নেওয়া।"
},
{
"id": 34,
"name_ar": "ٱلشَّهِيدُ",
"name_bn": "আশ-শাহীদ",
"meaning_bn": "প্রত্যক্ষকারী, প্রত্যেক ঘটনার প্রত্যক্ষ সাক্ষী",
"virtues": "আশ-শাহীদ সবকিছুর সাক্ষী; ন্যায় ও অবিচার সবই তাঁর নজরে রয়েছ।",
"practices": "১) গোপন-প্রকাশ্য সব কাজেই সততা বজায় রাখা।\n২) অন্যায় দেখলে সত্যের পক্ষে সাক্ষ্য প্রদান করা।"
},
{
"id": 35,
"name_ar": "ٱلْحَقُّ",
"name_bn": "আল-হক্ক",
"meaning_bn": "সত্য, স্থায়ী বাস্তবতা",
"virtues": "আল-হক্ক হচ্ছে পরম সত্য; যা শাশ্বত ও অবিচল। মানবজগতের ধ্যান-ধারণা ও নীতির ভিত্তি এটিই।",
"practices": "১) সত্যভিত্তিক বক্তব্য ও কাজ করা।\n২) মিথ্যা ও প্রতারণা থেকে বিরত থাকা।"
},
{
"id": 36,
"name_ar": "ٱلْوَكِيلُ",
"name_bn": "আল-ওকীল",
"meaning_bn": "অভিভাবক ও নির্ভরযোগ্য পৃষ্ঠপোষক",
"virtues": "আল-ওকীল প্রতিটি মানুষের অনিয়ন্ত্রিত পরিস্থিতিতে সহায়ক; তিনি যাঁকে ভরসা করে তিনি নিরাপদ।",
"practices": "১) কাজ শুরু পূর্বে আল্লাহর ওপর ভরসা (তাওয়াক্কুল) স্থাপন করা।\n২) নিজের প্রচেষ্টা ও আল্লাহর সহায়তা মিলিয়ে এগোন।"
},
{
"id": 37,
"name_ar": "ٱلْقَوِيُّ",
"name_bn": "আল-ক্বওয়িউ",
"meaning_bn": "অতিশক্তিশালী, জোরালো",
"virtues": "আল-ক্বওয়িউ সমস্ত শক্তির উৎস; তিনি দুর্বলতাকে শক্তিতে রূপান্তর করতে পারেন।",
"practices": "১) দুর্বলতায় আল্লাহর শক্তি চাওয়া।\n২) শক্তি পেলে দয়াশীল ও ন্যায়পরায়ণ হওয়া।"
},
{
"id": 38,
"name_ar": "ٱلْمَتِينُ",
"name_bn": "আল-মতীন",
"meaning_bn": "অটল, অবিচল ও দৃঢ়",
"virtues": "আল-মতীন শক্তির স্থায়িত্ব; তিনি সবকিছুকে দৃঢ়ভাবে ধারণ করছেন।",
"practices": "১) বিপদে ধৈর্য ধারণ করে আল্লাহর সাহায্য প্রার্থনা করা।\n২) নৈতিক দৃঢ়তা বজায় রাখা।"
},
{
"id": 39,
"name_ar": "ٱلْوَلِيُّ",
"name_bn": "আল-ওলীয়",
"meaning_bn": "সন্তোষজনক সহায়ক ও বন্ধু",
"virtues": "আল-ওলীয় বিশ্বাসীদের নিকটবর্তী সহায়ক; তিনি স্নেহে ও যত্নে রেখেন।",
"practices": "১) আল্লাহকে নিজের পরম বন্ধু মনে করে ভরসা করা।\n২) অন্যের প্রতি সহানুভূতি ও সাহায্য বাড়ানো।"
},
{
"id": 40,
"name_ar": "ٱلْحَمِيدُ",
"name_bn": "আল-হামীদ",
"meaning_bn": "প্রশংসিত — প্রশংসার যোগ্য",
"virtues": "আল-হামীদ সকল প্রশংসার যোগ্য; তাঁকে ধন্যবাদ ও কৃতজ্ঞতা জানানো উচিত।",
"practices": "১) সফলতা ও বরকত পেলে আল্লাহকে স্মরণ করা (আলহামদুলিল্লাহ)।\n২) প্রতিদিন কৃতজ্ঞতা অনুশীলন করা।"
},
{
"id": 41,
"name_ar": "ٱلْمُحْصِي",
"name_bn": "আল-মুহসী",
"meaning_bn": "পরিমাপক, প্রতিটি কাজ ও ব্যাপকতার হিসাব রাখেন",
"virtues": "আল-মুহসী প্রতিটি কাজ ও ঘটনার সঠিক হিসাব রাখেন; কোন কিছুই অদৃশ্য নয়।",
"practices": "১) নিজের আমলের হিসাব করে সংশোধন করা।\n২) আমল রেকর্ড করে নৈতিক ও স্পষ্ট জীবনযাপন করা।"
},
{
"id": 42,
"name_ar": "ٱلْمُبْدِئُ",
"name_bn": "আল-মুব্দী'",
"meaning_bn": "প্রথম স্রষ্টা, শুরুকারী",
"virtues": "আল-মুব্দী' সৃষ্টির সূচনা করেছেন; সবকিছুর আদিপ্রকাশ।",
"practices": "১) নতুন কাজ শুরুতে আল্লাহর দোয়া ও সহায়তা চাওয়া।\n২) জীবনের প্রতিটি সূচনায় আল্লাহর স্মরণ রাখা।"
},
{
"id": 43,
"name_ar": "ٱلْمُعِيدُ",
"name_bn": "আল-মুআদ্দি",
"meaning_bn": "পুনরুদ্ধারকারী, পুনরায় ফিরিয়ে আনে",
"virtues": "আল-মুআদ্দি পুনরায় জীবন দেওয়ার ক্ষমতা রাখেন; তিনি পুনরুত্থান ও পুনরায় শুরু আদায় করেন।",
"practices": "১) আখেরাতের জন্য প্রস্তুতি নেওয়া।\n২) ভুল থেকে ফিরে এসে নতুন করে জীবন গঠন করা।"
},
{
"id": 44,
"name_ar": "ٱلْمُحْيِي",
"name_bn": "আল-মুহ্যি",
"meaning_bn": "জীবন দানকারী",
"virtues": "আল-মুহ্যি জীবনের স্রষ্টা ও জীবনীশক্তির উৎস; তিনি প্রাণ দিয়েছেন এবং জীবন নিয়ন্ত্রণ করেন।",
"practices": "১) প্রতিদিন জীবনের জন্য আল্লাহকে ধন্যবাদ জানানো।\n২) জীবনের সন্তুষ্টি ও দানশীলতা বৃদ্ধি করা।"
},
{
"id": 45,
"name_ar": "ٱلْمُمِيتُ",
"name_bn": "আল-মুমিত",
"meaning_bn": "মৃত্যু প্রদানকারী",
"virtues": "আল-মুমিত জীবনের সমাপ্তি ও মৃত্যুর অধিপতি; তিনি জীবনের ফ্লো নিয়ন্ত্রণ করেন।",
"practices": "১) মৃত্যু স্মরণ করে নেক আমল বৃদ্ধি করা।\n২) পরের জন্য প্রস্তুতি ও তওবা রাখা।"
},
{
"id": 46,
"name_ar": "ٱلْحَيُّ",
"name_bn": "আল-হাইয়্যু",
"meaning_bn": "অমনোচ্ছলভাবে জীবিত, অনন্ত জীবিত",
"virtues": "আল-হাইয়্যু যে কখনো অচেতন হন না; তিনি চিরন্তন জীবন-উৎস।",
"practices": "১) আল্লাহর জীবন্তত্ব স্মরণ করে ধৈর্য ও দৃঢ়তা অর্জন করা।\n২) জীবনের প্রতিটি মুহূর্তকে মহিমান্বিত উপায়ে ব্যবহার করা।"
},
{
"id": 47,
"name_ar": "ٱلْقَيُّومُ",
"name_bn": "আল-কাইয়িউম",
"meaning_bn": "স্বয়ং-স্থিত, সমস্ত কিছুর রক্ষণকর্তা",
"virtues": "আল-কাইয়িউম সৃষ্টির সমগ্র পরিচালনাকারী; তিনি প্রতিটি কিছুকে রক্ষা ও চালান।",
"practices": "১) জীবনের প্রতিটি বিষয় আল্লাহর তত্ত্বাবধানে রেখে কাজ করা।\n২) সমস্যায় আল্লাহর ওপর ভরসা রাখা।"
},
{
"id": 48,
"name_ar": "ٱلْوَاجِدُ",
"name_bn": "আল-ওয়াজিদ",
"meaning_bn": "অবসানহীনভাবে পাওয়া — যে সবকিছু খুঁজে পান",
"virtues": "আল-ওয়াজিদ সব অবস্থায় উপস্থিত; তিনি আল্লাহর প্রতি সমগ্র উপলব্ধির প্রতীক।",
"practices": "১) সম্ভাব্য সমাধান খুঁজে পাওয়ার জন্য আল্লাহর দোয়া করা।\n২) জীবনে কৃতজ্ঞতা ও সৃজনশীলতা বৃদ্ধি করা।"
},
{
"id": 49,
"name_ar": "ٱلْمَاجِدُ",
"name_bn": "আল-মাজিদ",
"meaning_bn": "গৌরবশালী, মহান",
"virtues": "আল-মাজিদ মহান গৌরব ও মর্যাদায় পরিপূর্ণ; তিনি সম্মান ও গৌরবের উৎস।",
"practices": "১) আল্লাহর মহিমা স্মরণ করে নম্রতা বজায় রাখা।\n২) আল্লাহর গুণাবলি প্রচার করা ও সম্মান প্রদর্শন করা।"
},
{
"id": 50,
"name_ar": "ٱلْواحِدُ",
"name_bn": "আল-ওাহিদ",
"meaning_bn": "একমাত্র, অনন্য একত্ব",
"virtues": "আল-ওাহিদ আল্লাহর একত্বকে নির্দেশ করে—তিনি এক এবং অনন্য।",
"practices": "১) তৌহিদের শিক্ষা গ্রহণ ও প্রচার করা।\n২) বিশ্বাসকে একত্র করে রাখার প্রচেষ্টা করা।"
},
{
"id": 51,
"name_ar": "ٱلْاَحَدُ",
"name_bn": "আল-আহাদ",
"meaning_bn": "অদ্বিতীয়, নিজস্ব একত্ব",
"virtues": "আল-আহাদের একত্ব অচ্যাল; তিনি কোন অংশীদারহীন পরম সত্তা।",
"practices": "১) 'সুরা ইখলাস' পাঠের মাধ্যমে একত্ব অনুশীলন করা।\n২) দৈনন্দিন জীবনে আল্লাহর একত্ব বোঝানো ও প্রদর্শন করা।"
},
{
"id": 52,
"name_ar": "ٱلصَّمَدُ",
"name_bn": "আস-সামাদ",
"meaning_bn": "নির্ভরতার কেন্দ্র, সকলের প্রত্যয়স্থল",
"virtues": "আস-সামাদ প্রত্যেককেই নির্ভরশীল করে, কিন্তু তিনি কাউকের ওপর নির্ভর নন; সকলের চাহিদার পূর্ণতা তঁর দ্বারা।",
"practices": "১) আল্লাহর প্রতি সম্পূর্ণ নির্ভরতা ও ভরসা স্থাপন করা।\n২) নিজ জ্ঞান ও শক্তির অতিরিক্ত হওয়ার সময়ও আল্লাহকে স্মরণ করা।"
},
{
"id": 53,
"name_ar": "ٱلْقَادِرُ",
"name_bn": "আল-ক্বাদির",
"meaning_bn": "ক্ষমতাবান, সমুদ্রের মতো সক্ষম",
"virtues": "আল-ক্বাদির সর্বসিদ্ধ ক্ষমতাশালী; তিনি যা ইচ্ছা ঘটাতে পারেন।",
"practices": "১) ক্ষমতার জন্য দোয়া করলে আল্লাহর নির্দেশ মেনে ধৈর্য রাখা।\n২) ক্ষমতা পেলে ন্যায়পরায়ণভাবে ব্যবহার করা।"
},
{
"id": 54,
"name_ar": "ٱلْمُقْتَدِرُ",
"name_bn": "আল-মুক্তাদির",
"meaning_bn": "অতিপরাক্রমশালী, যিনি ব্যাপক ক্ষমতায় অধিষ্ঠিত",
"virtues": "আল-মুক্তাদির শক্তির পূর্ণতায় অধিষ্ঠিত; তিনি সমস্ত নিয়ন্ত্রণ পর্যবেক্ষণ করেন।",
"practices": "১) শক্তির মাঝে নম্রতা ধরে রাখা।\n২) কঠোর পরিস্থিতিতে আল্লাহর সহায়তা চাওয়া।"
},
{
"id": 55,
"name_ar": "ٱلْمُقَدِّمُ",
"name_bn": "আল-মুকাদ্দিম",
"meaning_bn": "যাকে সামনে আনেন, অগ্রসরকারী",
"virtues": "আল-মুকাদ্দিম যাকে ইচ্ছা, সামনে এনেন; তিনি মানুষের ভাগ্য এগিয়ে দিতে পারেন।",
"practices": "১) সঠিক সময়ে আল্লাহর নিকট সহায়তা চাইলে অগ্রগতি পাওয়া যায়—দোয়া করা।\n২) সুযোগ পেলে কৃতজ্ঞতা জানানো।"
},
{
"id": 56,
"name_ar": "ٱلْمُؤَخِّرُ",
"name_bn": "আল-মুআখির",
"meaning_bn": "পরে রাখেন, বিলম্বকারী",
"virtues": "আল-মুআখির সময় ও স্থিতি নির্ধারণ করেন; তিনি ইচ্ছা করে কিছুকে পিছিয়ে রাখতে পারেন।",
"practices": "১) ধৈর্য ধারণ ও আল্লাহর পরিকল্পনা মেনে চলা।\n২) শেষপর্যন্ত ঠিক সময়েই আল্লাহর ইচ্ছে মেনে কাজ করা।"
},
{
"id": 57,
"name_ar": "ٱلْأَوَّلُ",
"name_bn": "আল-আওয়াল",
"meaning_bn": "প্রথম, কোন শুরু তার বাইরে নেই",
"virtues": "আল-আওয়াল সবকিছুর প্রাথমিক উৎস; তিনি পূর্ববর্তী ও অনাদি।",
"practices": "১) জীবনে নতুন সূচনা আল্লাহর কাছে নিবেদন করা।\n২) সব কাজের মূল উদ্দেশ্য আল্লাহর সন্তুষ্টি রাখা।"
},
{
"id": 58,
"name_ar": "ٱلْآخِرُ",
"name_bn": "আল-আখির",
"meaning_bn": "শেষ, চূড়ান্ত",
"virtues": "আল-আখির সবকিছুর শেষ; আখেরাতের সিদ্ধান্ত তাঁরই হাতে।",
"practices": "১) দ্রুত ফলের আশায় না থেকে আখেরাতের প্রস্তুতি নেওয়া।\n২) দীর্ঘমেয়াদী নেক আমল বজায় রাখা।"
},
{
"id": 59,
"name_ar": "ٱلظَّاهِرُ",
"name_bn": "আল-জাহির",
"meaning_bn": "প্রকাশিত, স্পষ্ট",
"virtues": "আল-জাহির তাঁর প্রকাশ্য রূপে উপস্থিত; তিনি সবকিছুকে স্পষ্ট করেন।",
"practices": "১) সত্য ও ন্যায় প্রকাশে সাহসী হওয়া।\n২) দৃষ্টিনন্দন ও স্পষ্ট কাজের মাধ্যমে আল্লাহর রূপ প্রকাশ করা।"
},
{
"id": 60,
"name_ar": "ٱلْبَاطِنُ",
"name_bn": "আল-বাতিন",
"meaning_bn": "অন্তরীণ, গোপনীয়",
"virtues": "আল-বাতিন সবকিছুর অন্তর জেনে থাকেন; গোপন কাজও তাঁর কাছে প্রকাশ্য।",
"practices": "১) অন্তরের পরিশুদ্ধি বজায় রাখা।\n২) অন্তর থেকে সৎ উদ্দেশ্যকে বাড়ানো।"
},
{
"id": 61,
"name_ar": "ٱلْوَالِي",
"name_bn": "আল-ওয়ালী",
"meaning_bn": "রক্ষাকারী বন্ধু, বন্ধু ও সহায়ক",
"virtues": "আল-ওয়ালী বিশ্বাসীদের নিকটবর্তী সহায়ক; তিনি তাদের জন্য রক্ষা ও সহায়তা প্রদান করেন।",
"practices": "১) আল্লাহকে নিজের পরম সহচর মনে করে ভরসা রাখা।\n২) অন্যের সহায়তা ও বন্ধুত্বে উদ্যোগী হওয়া।"
},
{
"id": 62,
"name_ar": "ٱلْمُتَعَالِي",
"name_bn": "আল-মুতাইয়্যাল",
"meaning_bn": "পরম উচ্চশ্রেণী, অতুলনীয় উচ্চতা",
"virtues": "আল-মুতাইয়্যাল আল্লাহর অতুলনীয় উচ্চতা ও বিশুদ্ধতা প্রদর্শন করে; তিনি সম্পূর্ণ পরম ও আলাদা।",
"practices": "১) ভক্তি বাড়াতে কোরআন ও ইবাদত বৃদ্ধি করা।\n২) ভক্তিতে নম্রতা ও পরিশ্রম বাড়ানো।"
},
{
"id": 63,
"name_ar": "ٱلْبَرُّ",
"name_bn": "আল-বারু",
"meaning_bn": "পরম কল্যাণকারী, সদয়ভাবে কল্যাণকর কাজ করা",
"virtues": "আল-বারু পরম কল্যাণ ও সদাচারের উৎস; তিনি ভালোর ধারক।",
"practices": "১) ভালোর প্রচলন ও অন্যকে সাহায্য করা।\n২) আল্লাহর কল্যাণ স্মরণ করে দান করা ও সদকা বৃদ্ধি করা।"
},
{
"id": 64,
"name_ar": "ٱلْتَّوَّابُ",
"name_bn": "আত-তাওয়াব",
"meaning_bn": "পাপীকে দ্রুত তাওবা করিয়ে নেবেন, গ্রহণকারী তাওবা",
"virtues": "আত-তাওয়াব বারংবার তাওবার গ্রহণকারী; তিনি ব্যাকুল হৃদয়কে ক্ষমা দেন ও পুনরায় রাস্তা দেখান।",
"practices": "১) পাপ করলে দ্রুত তওবা করা।\n২) অন্যদের তওবার অনুপ্রেরণা প্রদান করা।\n৩) তাওবা রুটিন করে সময়-সময়ে আত্মসমীক্ষা করা।"
},
{
"id": 65,
"name_ar": "ٱلْمُنْتَقِمُ",
"name_bn": "আল-মুনতাকিম",
"meaning_bn": "শাস্তি প্রদায়ক, অন্যায়ের বিচারকারী",
"virtues": "আল-মুনতাকিম অন্যায় ও লঙ্ঘনকারীদের বিচার করেন; তিনি ন্যায় প্রতিষ্ঠা করে দেন।",
"practices": "১) ব্যক্তিগত প্রতিশোধ নেওয়ার আগ্রহ পরিহার করে আল্লাহর ন্যায়ে বিশ্বাস রাখা।\n২) অবিচার দেখতে পেলে ন্যায় প্রতিষ্ঠায় সহায়তা করা।"
},
{
"id": 66,
"name_ar": "ٱلْعَفُوُّ",
"name_bn": "আল-আফু",
"meaning_bn": "মুছে দেন, বিনষ্ট করে দেন (পাপকে বাদ দেয়া)",
"virtues": "আল-আফু পাপ মোচিতকারী; তিনি কোনো পাপকে মুছে ফেলতে পারেন এবং দণ্ড মওকুফ করেন।",
"practices": "১) দোষ স্বীকার করে আন্তরিকতা নিয়ে তওবা করা।\n২) অন্যের ভুল ক্ষমা করে আল্লাহকে স্মরণ করা।"
},
{
"id": 67,
"name_ar": "ٱلرَّؤُوفُ",
"name_bn": "আর-রউফ",
"meaning_bn": "অতিশয় দয়ালু ও কোমল হৃদয়সম্পন্ন",
"virtues": "আর-রউফ আল্লাহর কোমল দয়ালুতাকে চিহ্নিত করে; তিনি শ্রদ্ধাশীল ও দয়া প্রদর্শন করেন বিশেষত তাঁর বান্দাদের প্রতি।",
"practices": "১) দরমিয়ানে সহানুভূতি ও করুণা বাড়ানো।\n২) দয়া করে অন্যকে সাহায্য করার মাধ্যমে আল্লাহর রউফত্বের অনুসরণ করা।"
},
{
"id": 68,
"name_ar": "مَالِكُ ٱلْمُلْكِ",
"name_bn": "মালিকুল-মুল্ক",
"meaning_bn": "রাজ্যের সর্বাধিপতি — রাজ্য ও সৃষ্টির মালিক",
"virtues": "মালিকুল-মুল্ক সমস্ত রাজ্য ও ক্ষমতা ধারণ করেন; তাঁরই ইচ্ছায় পরিবর্তন ঘটে।",
"practices": "১) জীবনের বড় বিষয়গুলোতে আল্লাহর ইচ্ছে মেনে চলা।\n২) সম্পদ ও ক্ষমতা পেলে নম্রতা ও ন্যায় বজায় রাখা।"
},
{
"id": 69,
"name_ar": "ذُو الْجَلَالِ وَالْإِكْرَامِ",
"name_bn": "জুল-জালালি ওয়াল ইকরাম",
"meaning_bn": "মহিমায় ভরপুর এবং সম্মানিত — ঐশ্বরিক গৌরব ও আশা",
"virtues": "এই নাম আল্লাহর মহিমা ও সম্মানকে একসঙ্গে নির্দেশ করে; তিনি গৌরবময় ও অফুরন্ত অনুগ্রহী।",
"practices": "১) আল্লাহর সম্মান-গৌরব স্মরণ করে নম্রতা রাখা।\n২) দায়িত্ব ও মর্যাদায় পরিপূর্ণ কাজে সততা বজায় রাখা।"
},
{
"id": 70,
"name_ar": "ٱلْمُسْتَعَانُ",
"name_bn": "আল-মুস্তা'আন",
"meaning_bn": "সহায়তা প্রার্থিত — সাহায্যকারী",
"virtues": "আল-মুস্তা'আন সকল সহযোগিতার উৎস; যে কোনো বিপদে তাঁরই সাহায্য কাম্য।",
"practices": "১) যেখানে কঠিন মনে হয় আল্লাহর সাহায্য চাওয়া।\n২) নিজ প্রচেষ্টা ও আল্লাহর সাহায্যকে মিলিয়ে চেষ্টা চালানো।"
},
{
"id": 71,
"name_ar": "ٱلْبَاعِثُ",
"name_bn": "আল-বাসিত",
"meaning_bn": "প্রসারণকারী (সুমতি ও বিস্তার প্রদানকারী)",
"virtues": "আল-বাসিত মানুষের ওপর রহমত প্রসার করে; তিনি রিজিক, সুযোগ ও আলো বিস্তার করেন।",
"practices": "১) প্রাপ্ত সুযোগকে আল্লাহর দান মনে করে কৃতজ্ঞতা প্ৰকাশ করা।\n২) দান-পুন্য ও সহায়তায় অংশগ্রহণ করা।"
},
{
"id": 72,
"name_ar": "ٱلْخَافِضُ",
"name_bn": "আল-খাফিজ",
"meaning_bn": "নম্র করে ফেলার ক্ষমতা — (গর্বিতকে নীচে নামান)",
"virtues": "আল-খাফিজ উচ্চতা দানে ও দমনে সক্ষম; তিনি গোঁড়ামি ও অহংকারকে বিনষ্ট করতে পারেন।",
"practices": "১) অহংকার থেকে মুক্ত থাকার চেষ্টা করা।\n২) স্রষ্টার সম্মোহনে বিনয়ী হওয়া।"
},
{
"id": 73,
"name_ar": "ٱلْرَّافِعُ",
"name_bn": "আর-রাফি'",
"meaning_bn": "উত্তোলনকারী, মর্যাদা বৃদ্ধি করেন",
"virtues": "আর-রাফি' মানুষের মর্যাদা ও অবস্থান বাড়ান; তিনি সম্মান দান করেন।",
"practices": "১) নৈতিক ও ধর্মীয় কর্মকাণ্ডের মাধ্যমে মর্যাদা অর্জন করা।\n২) অন্যকে সম্মান দিয়ে তাদের উন্নতির পথ প্রশস্ত করা।"
},
{
"id": 74,
"name_ar": "ٱلْمُعِزُّ",
"name_bn": "আল-মুয্জিৎ",
"meaning_bn": "সম্মান ও সগৌরব প্রদানকারী",
"virtues": "আল-মুয্জিৎ আল্লাহই যে সম্মান দিয়ে থাকেন; তিনি আদর ও মর্যাদা দান করেন।",
"practices": "১) সম্মান প্রাপ্ত হলে কৃতজ্ঞতা ও নম্রতা প্রকাশ করা।\n২) অন্যকে সম্মান দিয়ে সমাজে ভ্রাতৃত্ব বৃদ্ধি করা।"
},
{
"id": 75,
"name_ar": "ٱلْمُذِلُّ",
"name_bn": "আল-মুযিল",
"meaning_bn": "বিজড়িত করা, অপমান করা (অন্যায় কাজের জন্য শাস্তি)",
"virtues": "আল-মুযিল যাকে ইচ্ছা করবেন তৎসময় অপরকে হ্রাস করেন; তিনি ‘ইজ্জত’ ও ‘অবমাননা’ নির্ধারণ করেন।",
"practices": "১) গর্বপূর্ণ আচরণ পরিহার করে নম্রতা বজায় রাখা।\n২) অন্যের প্রতি দয়া প্রদর্শন করা।"
},
{
"id": 76,
"name_ar": "ٱلْسَّمِيعُ",
"name_bn": "আস-সমী'",
"meaning_bn": "পরিপূর্ণ শুননাহীন নয়—সবকিছু শোনেন",
"virtues": "আস-সমী' সবকথা শুনেন; গোপন কিংবা প্রকাশ্য—কিছুই তাঁর নজর এড়ায় না।",
"practices": "১) গোপনে ও প্রকাশ্যে সৎ হওয়া—কারণ আল্লাহ শুনতে পান।\n২) দোয়াগুলো বিশ্বাস ও নম্রতায় করা।"
},
{
"id": 77,
"name_ar": "ٱلْبَصِيرُ",
"name_bn": "আল-বাসীর",
"meaning_bn": "ওচ্ছে দৃষ্টিশক্তি — প্রতিটি কিছুর পরিপূর্ণ দর্শনকারী",
"virtues": "আল-বাসীর সবকিছু দেখতে পান; ত্রুটি-ভুল কিংবা শুভ কর্ম—সবই তাঁর দৃষ্টির সামনে।",
"practices": "১) নিজের কর্ম-চিন্তা-ভাবনা পর্যালোচনা করে সংশোধন করা।\n২) অন্যের উপকারে দৃষ্টিভঙ্গি রাখার চেষ্টা করা।"
},
{
"id": 78,
"name_ar": "ٱلْحَكَمُ",
"name_bn": "আল-হাকাম",
"meaning_bn": "পরম রায়কার, ন্যায়-নির্ধারণকারী",
"virtues": "আল-হাকাম সর্বোত্তম বিচারক; তাঁর রায় ঠিক ও ন্যায়সংগত।",
"practices": "১) ভুল করলে আল্লাহর বিচারকে স্মরণ করে তওবা করা।\n২) সমাজে ন্যায় প্রতিষ্ঠায় অংশগ্রহণ করা।"
},
{
"id": 79,
"name_ar": "ٱلْعَدْلُ",
"name_bn": "আল-আদল",
"meaning_bn": "সম্পূর্ণ ন্যায়পরায়ণ, সুবিচারকারী",
"virtues": "আল-আদল ন্যায়ের অধিকারী; তিনি কখনো কৃপণ বা পক্ষপাতমূলক হবেন না।",
"practices": "১) বিচার ও আচরণে ন্যায্যতা বজায় রাখা।\n২) সুবিধাবঞ্চিতদের জন্য কণ্ঠস্বর প্রদান করা।"
},
{
"id": 80,
"name_ar": "ٱلْلَّطِيفُ",
"name_bn": "আল-লতীফ",
"meaning_bn": "সূক্ষ্মতায় কৃতদয়, নরম ও কোমল জ্ঞানে ভরা",
"virtues": "আল-লতীফ সূক্ষ্ম জ্ঞান এবং নরমবর্তিতা দিয়ে সাহায্য করেন; তিনি ভিন্নভাবে বন্ধুত্ত্ব দেখান।",
"practices": "১) সূক্ষ্ম দিকগুলো খেয়াল করে সদয় আচরণ করা।\n২) দয়া ও কোমলতা প্রদর্শন করে আল্লাহর লতিফত্ব অনুসরণ করা।"
},
{
"id": 81,
"name_ar": "ٱلْخَبِيرُ",
"name_bn": "আল-খাবীর",
"meaning_bn": "পরিপূর্ণ জ্ঞানের অধিকারী, সূক্ষ্ম জ্ঞান রাখেন",
"virtues": "আল-খাবীর সমস্ত গোপন ও প্রকাশ্য বিষয় জানেন; তিনি প্রত্যেককেই অভিজ্ঞতার আলোকে বিচার করেন।",
"practices": "১) নিজের কাজের ফলপ্রসূতা নিয়ে সচেতন হওয়া।\n২) আল্লাহর জ্ঞানে ভর করে সিদ্ধান্ত নেওয়া।"
},
{
"id": 82,
"name_ar": "ٱلْحَلِيمُ",
"name_bn": "আল-হলীম",
"meaning_bn": "ধৈর্যশীল, গৃহীতভাবে ক্ষমা করা",
"virtues": "আল-হলীম অত্যন্ত ধৈর্যশীল; তিনি তাড়াহুড়ো করে শাস্তি দেন না বরং সুযোগ দেন উত্তরণ করার।",
"practices": "১) ধৈর্যশীলতা অর্জন ও অন্তরের প্রশান্তি বাড়ানো।\n২) অপরের ভুলে সহনশীল হওয়া এবং ক্ষমা করা।"
},
{
"id": 83,
"name_ar": "ٱلْعَظِيمُ",
"name_bn": "আল-আজীম",
"meaning_bn": "বিশাল ও মহৎ",
"virtues": "আল-আজীম মহান ও অতুলনীয়; তিনি সব মহান কাজের উৎস।",
"practices": "১) আল্লাহর মহানতাকে স্মরণ করে নিজের কাজকে সজ্জিত করা।\n২) ভক্তিভাবে তাঁর গুণাবলি প্রচার করা।"
},
{
"id": 84,
"name_ar": "ٱلْغَفُورُ",
"name_bn": "আল-গফূর",
"meaning_bn": "অতিশয় ক্ষমাশীল (গুণে গভীর ক্ষমা প্রদানকারী)",
"virtues": "আল-গফূর বারবার ক্ষমা করে দেন; তাঁর ক্ষমা অপরিসীম।",
"practices": "১) পাপ করলে আন্তরিক তওবা করা।\n২) অন্যকে ক্ষমা ও সহানুভূতি প্রদর্শন করা।"
},
{
"id": 85,
"name_ar": "ٱلْشَّكُورُ",
"name_bn": "আশ-শাকূর",
"meaning_bn": "কৃতজ্ঞতা গ্রহনকারী ও পুরস্কৃতকারী",
"virtues": "আশ-শাকূর কৃতজ্ঞতার মূল্যকে জানেন; তিনি সামান্য শ্রদ্ধা দেখালেই পুরস্কৃত করেন।",
"practices": "১) প্রতিদিন নেক কাজগুলো নিয়মিত করা, যাতে আল্লাহর কাছে কৃতজ্ঞতা বৃদ্ধি পায়।\n২) ছোট ভালো কাজে আল্লাহর পুরস্কার আশা করা ও ধন্যবাদ জানানো।"
},
{
"id": 86,
"name_ar": "ٱلْعَلِىِّ",
"name_bn": "আল-আলী",
"meaning_bn": "উচ্চতম ও শ্রেষ্ঠ",
"virtues": "আল-আলী আল্লাহর উচ্চতা ও শ্রেষ্ঠতাকে ব্যক্ত করে; তিনি সর্বোচ্চ মর্যাদার অধিকারী।",
"practices": "১) আল্লাহর উচ্চ মর্যাদা উপলব্ধি করে তার নির্দেশ মেনে চলা।\n২) নিজকে উন্নততর করে আল্লাহর কাছে উপস্থাপন করা।"
},
{
"id": 87,
"name_ar": "ٱلْكَبِيرُ",
"name_bn": "আল-কবীর",
"meaning_bn": "অতি-বৃহৎ (আগের তালিকার অনুরূপ)",
"virtues": "আল-কবীরের মহত্ত্ব সীমাহীন; তিনি সর্বসর্বে মহান।",
"practices": "১) সৃষ্টির বিস্ময় দেখে কৃতজ্ঞতা প্রকাশ করা।"
},
{
"id": 88,
"name_ar": "ٱلْحَفِيظُ",
"name_bn": "আল-হাফিজ (পুনরাবৃত্তি)",
"meaning_bn": "রক্ষাকারী ও সংরক্ষণকারী",
"virtues": "আল-হাফিজ সবকিছু রক্ষা ও নিরাপদ রাখেন; পুনরায় রূপকল্পে এ নামের গুরুত্ব ব্যাখ্যাযোগ্য।",
"practices": "১) নিরাপত্তা প্রার্থনা করা ও আল্লাহর উপর ভরসা রাখা।"
},
{
"id": 89,
"name_ar": "ٱلْمُقِتُ",
"name_bn": "আল-মুকীত (পুনরাবৃত্তি)",
"meaning_bn": "জীবিকা ও সহায়তা প্রদানকারী",
"virtues": "আল-মুকীত মানুষের দৈনন্দিন জীবন রক্ষায় সক্রিয়।",
"practices": "১) রুজির জন্য আল্লাহর কাছে কৃতজ্ঞতা ও প্রার্থনা করা।"
},
{
"id": 90,
"name_ar": "ٱلْحَسِيبُ",
"name_bn": "আল-হাসিব (পুনরাবৃত্তি)",
"meaning_bn": "হিসাবকর্তা",
"virtues": "আল-হাসিব প্রতিটি আমলের হিসাব রাখেন এবং সঠিক পরিণতি দেন।",
"practices": "১) আমল-হিসাব করে সংশোধন করা।"
},
{
"id": 91,
"name_ar": "ٱلْجَلِيلُ",
"name_bn": "আল-জালীল (পুনরাবৃত্তি)",
"meaning_bn": "মহিমান্বিত",
"virtues": "আল-জালীল মহিমা ও মর্যাদায় পরিপূর্ণ।",
"practices": "১) আল্লাহর মর্যাদা সম্মান করে ইবাদত করা।"
},
{
"id": 92,
"name_ar": "ٱلْكَرِيمُ",
"name_bn": "আল-করীম (পুনরাবৃত্তি)",
"meaning_bn": "উদার ও দয়াশীল",
"virtues": "আল-করীম অনুগ্রহের মাধ্যমে পুরস্কার দেন।",
"practices": "১) দান ও দয়ার কাজ করা।"
},
{
"id": 93,
"name_ar": "ٱلْرَّقِيبُ",
"name_bn": "আর-রকীব (পুনরাবৃত্তি)",
"meaning_bn": "পর্যবেক্ষক",
"virtues": "আর-রকীব সবকিছু পর্যবেক্ষণ করে থাকেন।",
"practices": "১) গোপনেও সৎ থাকা।"
},
{
"id": 94,
"name_ar": "ٱلْمُجِيبُ",
"name_bn": "আল-মুজীব (পুনরাবৃত্তি)",
"meaning_bn": "দোয়া কবুলকারী",
"virtues": "আল-মুজীব প্রার্থনার সাড়া দেন।",
"practices": "১) দোয়া ও ধৈর্য ধরে রাখা।"
},
{
"id": 95,
"name_ar": "ٱلْوَاسِعُ",
"name_bn": "আল-ওয়াসি' (পুনরাবৃত্তি)",
"meaning_bn": "প্রশস্ততা-সম্পন্ন",
"virtues": "আল-ওয়াসি' রহমত ও প্রশস্ততার উৎস।",
"practices": "১) দানে উদার হওয়া ও আল্লাহর প্রশস্ততায় ভরসা রাখা।"
},
{
"id": 96,
"name_ar": "ٱلْحَكِيمُ",
"name_bn": "আল-হাকীম (পুনরাবৃত্তি)",
"meaning_bn": "পরম বিচক্ষণ ও জ্ঞাত",
"virtues": "আল-হাকীম সকল নীতির সর্বোত্তম রূপদাতা।",
"practices": "১) সিদ্ধান্ত নেওয়ার আগে জ্ঞান অর্জন করা।"
},
{
"id": 97,
"name_ar": "ٱلْوَدُودُ",
"name_bn": "আল-ওদুদ (পুনরাবৃত্তি)",
"meaning_bn": "অত্যন্ত প্রেমময়",
"virtues": "আল-ওদুদ মানুষের প্রতি অশেষ প্রেম দেখান।",
"practices": "১) ভক্তি ও সদাচার বাড়ানো।"
},
{
"id": 98,
"name_ar": "ٱلْمَجِيدُ",
"name_bn": "আল-মাজিদ (পুনরাবৃত্তি)",
"meaning_bn": "মহিমান্বিত",
"virtues": "আল-মাজিদের মহিমা আখেরে ও দুনিয়াতে ব্যাপক।",
"practices": "১) আল্লাহর গুণগান করে জীবন সাজানো।"
},
{
"id": 99,
"name_ar": "ٱلْبَارِئُ",
"name_bn": "আল-বারি' (পুনরাবৃত্তি)",
"meaning_bn": "উপাখাক্তা, সঠিক রূপে সৃষ্টিকর্তা",
"virtues": "আল-বারির সৃষ্টি পরিকল্পনায় সুসামঞ্জস্য ও উদ্দেশ্য বিদ্যমান।",
"practices": "১) সৃষ্টির যত্নে অংশ নেওয়া ও আল্লাহর রচনায় কৃতজ্ঞ থাকা।"
}
]
}
